run.py
wrap.py
Pred_in_Open_Env-1.0.1.dist-info/LICENSE
Pred_in_Open_Env-1.0.1.dist-info/METADATA
Pred_in_Open_Env-1.0.1.dist-info/WHEEL
Pred_in_Open_Env-1.0.1.dist-info/top_level.txt
Pred_in_Open_Env-1.0.1.dist-info/RECORD
