Metadata-Version: 2.1
Name: Pred_in_Open_Env
Version: 1.0.1
Summary: A model to predict pedestrian flow in open environment
Author: hzy
Author-email: bbts123@sjtu.edu.cn
Requires-Python: >=3.8
License-File: LICENSE
Requires-Dist: numpy
Requires-Dist: pandas
Requires-Dist: scikit-learn
Requires-Dist: torch ==2.2.2
Requires-Dist: matplotlib
